[
    {
        "id": "202305050942685266",
        "title": "am/is的过去式？",
        "option": [],
        "answer": "was",
        "analysis": ""
    },
    {
        "id": "20230505094247298",
        "title": " are的过去式？",
        "option": [],
        "answer": "were",
        "analysis": ""
    },
    {
        "id": "202305050942910350",
        "title": "become的过去式？",
        "option": [],
        "answer": "became",
        "analysis": ""
    },
    {
        "id": "202305050942848943",
        "title": "begin的过去式？",
        "option": [],
        "answer": "began",
        "analysis": ""
    },
    {
        "id": "202305050942372459",
        "title": "break的过去式？",
        "option": [],
        "answer": "broke",
        "analysis": ""
    },
    {
        "id": "202305050942797561",
        "title": "bring的过去式？",
        "option": [],
        "answer": "brought ",
        "analysis": ""
    },
    {
        "id": "202305050942203881",
        "title": "build的过去式？",
        "option": [],
        "answer": "built",
        "analysis": ""
    },
    {
        "id": "202305050942750504",
        "title": "buy的过去式？",
        "option": [],
        "answer": "bought",
        "analysis": ""
    },
    {
        "id": "202305050942133533",
        "title": "can的过去式？",
        "option": [],
        "answer": "could",
        "analysis": ""
    },
    {
        "id": "202305050942823277",
        "title": "catch的过去式？",
        "option": [],
        "answer": "caught",
        "analysis": ""
    },
    {
        "id": "202305050942458255",
        "title": "choose的过去式？",
        "option": [],
        "answer": "chose",
        "analysis": ""
    },
    {
        "id": "202305050942115502",
        "title": "come的过去式？",
        "option": [],
        "answer": "came",
        "analysis": ""
    },
    {
        "id": "202305050942949253",
        "title": "do的过去式？",
        "option": [],
        "answer": "did",
        "analysis": ""
    },
    {
        "id": "202305050942523551",
        "title": "draw的过去式？",
        "option": [],
        "answer": "drew",
        "analysis": ""
    },
    {
        "id": "202305050942889580",
        "title": "drink的过去式？",
        "option": [],
        "answer": "drank",
        "analysis": ""
    },
    {
        "id": "202305050942236867",
        "title": "drive的过去式？",
        "option": [],
        "answer": "drove",
        "analysis": ""
    },
    {
        "id": "202305050942541193",
        "title": "eat的过去式？",
        "option": [],
        "answer": "ate",
        "analysis": ""
    },
    {
        "id": "202305050942555477",
        "title": "feel的过去式？",
        "option": [],
        "answer": "felt",
        "analysis": ""
    },
    {
        "id": "202305050942117495",
        "title": "find的过去式？",
        "option": [],
        "answer": "found",
        "analysis": ""
    },
    {
        "id": "202305050942458697",
        "title": "fly的过去式？",
        "option": [],
        "answer": "flew",
        "analysis": ""
    },
    {
        "id": "202305050942210952",
        "title": "get的过去式？",
        "option": [],
        "answer": "got",
        "analysis": ""
    },
    {
        "id": "202305050942905066",
        "title": "give的过去式？",
        "option": [],
        "answer": "gave",
        "analysis": ""
    },
    {
        "id": "202305050942585548",
        "title": "go的过去式？",
        "option": [],
        "answer": "went",
        "analysis": ""
    },
    {
        "id": "20230505094210466",
        "title": "have的过去式？",
        "option": [],
        "answer": "had",
        "analysis": ""
    },
    {
        "id": "202305050942529605",
        "title": "has的过去式？",
        "option": [],
        "answer": "had",
        "analysis": ""
    },
    {
        "id": "202305050942905582",
        "title": "hear的过去式？",
        "option": [],
        "answer": "heard",
        "analysis": ""
    },
    {
        "id": "202305050942764485",
        "title": "hold的过去式？",
        "option": [],
        "answer": "held",
        "analysis": ""
    },
    {
        "id": "20230505094253467",
        "title": "know的过去式？",
        "option": [],
        "answer": "knew",
        "analysis": ""
    },
    {
        "id": "20230505094282156",
        "title": "learn的过去式短的？",
        "option": [],
        "answer": "learnt",
        "analysis": ""
    },
    {
        "id": "202305050942740725",
        "title": "learn的过去式长的？",
        "option": [],
        "answer": "learned",
        "analysis": ""
    },
    {
        "id": "20230505094289572",
        "title": "leave的过去式？",
        "option": [],
        "answer": "left",
        "analysis": ""
    },
    {
        "id": "20230505094231035",
        "title": "let的过去式？",
        "option": [],
        "answer": "let",
        "analysis": ""
    },
    {
        "id": "20230505094276997",
        "title": "lie的过去式？",
        "option": [],
        "answer": "lay",
        "analysis": ""
    },
    {
        "id": "202305050942677827",
        "title": "lose的过去式？",
        "option": [],
        "answer": "lost",
        "analysis": ""
    },
    {
        "id": "202305050942547592",
        "title": "make的过去式？",
        "option": [],
        "answer": "made",
        "analysis": ""
    },
    {
        "id": "202305050942463333",
        "title": "may的过去式？",
        "option": [],
        "answer": "might",
        "analysis": ""
    },
    {
        "id": "202305050942970820",
        "title": "mean的过去式？",
        "option": [],
        "answer": "meant",
        "analysis": ""
    },
    {
        "id": "202305050942205192",
        "title": "meet的过去式？",
        "option": [],
        "answer": "met",
        "analysis": ""
    },
    {
        "id": "202305050942711548",
        "title": "pay的过去式？",
        "option": [],
        "answer": "paid",
        "analysis": ""
    },
    {
        "id": "202305050942378717",
        "title": "put的过去式？",
        "option": [],
        "answer": "put",
        "analysis": ""
    },
    {
        "id": "202305050942810308",
        "title": "read的过去式？",
        "option": [],
        "answer": "read",
        "analysis": ""
    },
    {
        "id": "202305050942212593",
        "title": "ride的过去式？",
        "option": [],
        "answer": "rode",
        "analysis": ""
    },
    {
        "id": "202305050942833109",
        "title": "rise的过去式？",
        "option": [],
        "answer": "rose",
        "analysis": ""
    },
    {
        "id": "202305050942111692",
        "title": "run的过去式？",
        "option": [],
        "answer": "ran",
        "analysis": ""
    },
    {
        "id": "202305050942968035",
        "title": "say的过去式？",
        "option": [],
        "answer": "said",
        "analysis": ""
    },
    {
        "id": "202305050942338369",
        "title": "see的过去式？",
        "option": [],
        "answer": "saw",
        "analysis": ""
    },
    {
        "id": "202305050942485053",
        "title": "sell的过去式？",
        "option": [],
        "answer": "sold",
        "analysis": ""
    },
    {
        "id": "202305050942848693",
        "title": "send的过去式？",
        "option": [],
        "answer": "sent",
        "analysis": ""
    },
    {
        "id": "202305050942211631",
        "title": "shake的过去式？",
        "option": [],
        "answer": "shook",
        "analysis": ""
    },
    {
        "id": "202305050942753985",
        "title": "shall的过去式？",
        "option": [],
        "answer": "should",
        "analysis": ""
    },
    {
        "id": "202305050942173453",
        "title": "sing的过去式？",
        "option": [],
        "answer": "sang",
        "analysis": ""
    },
    {
        "id": "20230505094223027",
        "title": "sit的过去式？",
        "option": [],
        "answer": "sat",
        "analysis": ""
    },
    {
        "id": "202305050942960291",
        "title": "speak的过去式？",
        "option": [],
        "answer": "spoke",
        "analysis": ""
    },
    {
        "id": "20230505094210308",
        "title": "spell的过去式短的？",
        "option": [],
        "answer": "spelt",
        "analysis": ""
    },
    {
        "id": "202305050942895508",
        "title": "spell的过去式长的？",
        "option": [],
        "answer": "spelled",
        "analysis": ""
    },
    {
        "id": "202305050942995707",
        "title": "spend的过去式？",
        "option": [],
        "answer": "spent",
        "analysis": ""
    },
    {
        "id": "202305050942518997",
        "title": "stand的过去式？",
        "option": [],
        "answer": "stood",
        "analysis": ""
    },
    {
        "id": "202305050942359689",
        "title": "sweep的过去式？",
        "option": [],
        "answer": "swept",
        "analysis": ""
    },
    {
        "id": "202305050942419779",
        "title": "swim的过去式？",
        "option": [],
        "answer": "swam",
        "analysis": ""
    },
    {
        "id": "202305050942636010",
        "title": "take的过去式？",
        "option": [],
        "answer": "took",
        "analysis": ""
    },
    {
        "id": "202305050942700608",
        "title": "teach的过去式？",
        "option": [],
        "answer": "taught",
        "analysis": ""
    },
    {
        "id": "202305050942636576",
        "title": "tell的过去式短的？",
        "option": [],
        "answer": "told",
        "analysis": ""
    },
    {
        "id": "202305050942982873",
        "title": "think的过去式短的？",
        "option": [],
        "answer": "thought",
        "analysis": ""
    },
    {
        "id": "202305050942740621",
        "title": "wear的过去式？",
        "option": [],
        "answer": "wore",
        "analysis": ""
    },
    {
        "id": "202305050942190052",
        "title": "will的过去式？",
        "option": [],
        "answer": "would",
        "analysis": ""
    },
    {
        "id": "202305050942394705",
        "title": "win的过去式？",
        "option": [],
        "answer": "won",
        "analysis": ""
    },
    {
        "id": "202305050942466279",
        "title": "write的过去式？",
        "option": [],
        "answer": "wrote",
        "analysis": ""
    }
]
